<xliffext:root xmlns:xliffext="urn:microsoft:content:schema:xliffextensions">
  <xliffext:skl>
    <xliffext:mroot>
      <xliffext:mta>
        <xliffext:name>name</xliffext:name>
        <xliffext:value>%%%1%%%</xliffext:value>
        <xliffext:type>System.String</xliffext:type>
      </xliffext:mta>
    </xliffext:mroot>
    <xliffext:content>
      <markdown_skeleton_root>
        <block_element>
          <MarkdownContent xmlns:xsi="http://www.w3.org/2001/XMLSchema-instance" xmlns:xsd="http://www.w3.org/2001/XMLSchema">
            <MarkdownParagraphBlock item_id="f3e744f7-4bc8-42ad-a08f-4150b51c457b" item_type="NormalParagraph">
              <paragraph_segments>
                <MarkdownSegment>
                  <SegmentId>d492c1bb-b8e0-4eb4-b2b7-e1129ef89e07</SegmentId>
                  <InternalNormalItem internal_item_id="9a41814a-a154-40da-9000-06a34e2acca2" internal_item_type="Normal">
                    <internalitemvalue>%%%2%%% 
    %%%3%%%</internalitemvalue>
                  </InternalNormalItem>
                </MarkdownSegment>
              </paragraph_segments>
            </MarkdownParagraphBlock>
            <MarkdownParagraphBlock item_id="5019cee6-0bd4-47b2-bf7e-69f3939d3940" item_type="NormalParagraph">
              <paragraph_segments>
                <MarkdownSegment>
                  <SegmentId>46bf327d-6431-4a51-856d-08a88d395e62</SegmentId>
                  <InternalNormalItem internal_item_id="9acaa98f-eca7-4ebd-8fae-8b7c45d71802" internal_item_type="Normal">
                    <internalitemvalue>%%%4%%%</internalitemvalue>
                  </InternalNormalItem>
                </MarkdownSegment>
              </paragraph_segments>
            </MarkdownParagraphBlock>
            <MarkdownHeaderBlock item_id="d0a3828c-3cfb-46e0-87fb-4b7a0bbdb6b0" item_type="Header">
              <headervalue>%%%5%%%</headervalue>
              <header_type>Star</header_type>
              <header_level>1</header_level>
            </MarkdownHeaderBlock>
            <MarkdownParagraphBlock item_id="baf76838-960a-42da-82d1-533147fdf867" item_type="NormalParagraph">
              <paragraph_segments>
                <MarkdownSegment>
                  <SegmentId>ae90e985-eecb-447d-a4e0-2a88b340caa3</SegmentId>
                  <InternalNormalItem internal_item_id="6b69c293-ce65-45f7-8ac2-acb8242e5165" internal_item_type="Normal">
                    <internalitemvalue>%%%6%%%</internalitemvalue>
                  </InternalNormalItem>
                </MarkdownSegment>
                <MarkdownSegment>
                  <SegmentId>542a0277-1948-4b5e-85ce-eb2c8efff7ff</SegmentId>
                  <InternalNormalItem internal_item_id="e340c851-18e4-4cca-9edf-677d0317613a" internal_item_type="Normal">
                    <internalitemvalue>%%%7%%%</internalitemvalue>
                  </InternalNormalItem>
                </MarkdownSegment>
              </paragraph_segments>
            </MarkdownParagraphBlock>
            <MarkdownParagraphBlock item_id="16e4b00a-4321-4885-a479-09617fc5347e" item_type="NormalParagraph">
              <paragraph_segments>
                <MarkdownSegment>
                  <SegmentId>657164c2-b3b0-42cd-90cf-973853a7e940</SegmentId>
                  <InternalNormalItem internal_item_id="cde7c00d-231a-4578-8970-6c4d7718c766" internal_item_type="Normal">
                    <internalitemvalue>%%%8%%%</internalitemvalue>
                  </InternalNormalItem>
                </MarkdownSegment>
                <MarkdownSegment>
                  <SegmentId>0efdb3f7-d3d0-454c-b435-a9813f97503e</SegmentId>
                  <LinkItem internal_item_id="af089e32-4b68-4f3b-a649-e9efe19070c8" internal_item_type="Link">
                    <internal_link_type>Inline</internal_link_type>
                    <internal_link_text>%%%9%%%</internal_link_text>
                    <internal_link_url>http://azure.microsoft.com/documentation/services/app-service/</internal_link_url>
                    <internal_link_title />
                  </LinkItem>
                  <InternalNormalItem internal_item_id="011feafd-0652-44ef-8cfe-3f9ad62cc74e" internal_item_type="Normal">
                    <internalitemvalue>%%%10%%%</internalitemvalue>
                  </InternalNormalItem>
                </MarkdownSegment>
              </paragraph_segments>
            </MarkdownParagraphBlock>
            <MarkdownHeaderBlock item_id="7d5cd9d7-91f7-449b-8182-fe21ce8e41d8" item_type="Header">
              <headervalue>%%%11%%%</headervalue>
              <header_type>Star</header_type>
              <header_level>2</header_level>
            </MarkdownHeaderBlock>
            <MarkdownParagraphBlock item_id="0c9e7cce-36de-4b5e-a8d8-6f2ad2f6d9e8" item_type="NormalParagraph">
              <paragraph_segments>
                <MarkdownSegment>
                  <SegmentId>abd40e7d-2d00-4280-a72e-4ed4cb1cb17f</SegmentId>
                  <InternalNormalItem internal_item_id="6b6c10ce-a406-49b5-bb11-a225869f5926" internal_item_type="Normal">
                    <internalitemvalue>%%%12%%%</internalitemvalue>
                  </InternalNormalItem>
                </MarkdownSegment>
              </paragraph_segments>
            </MarkdownParagraphBlock>
            <MarkdownListBlock item_id="c3f9ec5c-8fb1-4d6b-886b-b6d787fa31bc" item_type="List">
              <inner_list_items>
                <ListItem>
                  <MarkdownParagraphBlock item_id="8095e358-c505-49b1-9d1e-3fedcc45828b" item_type="NormalParagraph">
                    <paragraph_segments>
                      <MarkdownSegment>
                        <SegmentId>27c20886-7647-424e-9c31-54ecf990fe6b</SegmentId>
                        <BoldItem internal_item_id="b42eab89-7a33-42ba-9610-644dfd5d5170" internal_item_type="Bold">
                          <boldvalue>%%%13%%%</boldvalue>
                          <internal_itatic_bold_item_type>Star</internal_itatic_bold_item_type>
                        </BoldItem>
                        <InternalNormalItem internal_item_id="50ac6e94-8bc5-473d-870f-1d6640cd836c" internal_item_type="Normal">
                          <internalitemvalue>%%%14%%%</internalitemvalue>
                        </InternalNormalItem>
                      </MarkdownSegment>
                      <MarkdownSegment>
                        <SegmentId>aaf1bd25-90d3-4c42-92f8-29777597ee0e</SegmentId>
                        <InternalNormalItem internal_item_id="ecac644f-ff1a-495f-95ce-877f1465938a" internal_item_type="Normal">
                          <internalitemvalue>%%%15%%%</internalitemvalue>
                        </InternalNormalItem>
                      </MarkdownSegment>
                      <MarkdownSegment>
                        <SegmentId>0d6ecf4c-9eb4-4e77-b09a-b3860bacae90</SegmentId>
                        <InternalNormalItem internal_item_id="b6e4c53e-6565-429d-8175-447a7b0fff2b" internal_item_type="Normal">
                          <internalitemvalue>%%%16%%%</internalitemvalue>
                        </InternalNormalItem>
                      </MarkdownSegment>
                    </paragraph_segments>
                  </MarkdownParagraphBlock>
                </ListItem>
                <ListItem>
                  <MarkdownParagraphBlock item_id="890ed5f2-5aa9-4a48-bc5f-2b655fcad259" item_type="NormalParagraph">
                    <paragraph_segments>
                      <MarkdownSegment>
                        <SegmentId>0814b740-4d73-41c4-b231-af4d769719c9</SegmentId>
                        <BoldItem internal_item_id="6f7c163d-777d-479e-be30-e5da1ce5a6b5" internal_item_type="Bold">
                          <boldvalue>%%%17%%%</boldvalue>
                          <internal_itatic_bold_item_type>Star</internal_itatic_bold_item_type>
                        </BoldItem>
                        <InternalNormalItem internal_item_id="5cc78f6c-5ac4-4e1b-a868-b06ee802f436" internal_item_type="Normal">
                          <internalitemvalue>%%%18%%%</internalitemvalue>
                        </InternalNormalItem>
                      </MarkdownSegment>
                      <MarkdownSegment>
                        <SegmentId>acb95676-538d-4dbc-bf2e-e2130ab11fef</SegmentId>
                        <InternalNormalItem internal_item_id="21ef8134-2ec8-4807-85de-01efe77407dc" internal_item_type="Normal">
                          <internalitemvalue>%%%19%%%</internalitemvalue>
                        </InternalNormalItem>
                      </MarkdownSegment>
                    </paragraph_segments>
                  </MarkdownParagraphBlock>
                </ListItem>
                <ListItem>
                  <MarkdownParagraphBlock item_id="55fba913-a663-423e-b0e4-5ff80e6d3c41" item_type="NormalParagraph">
                    <paragraph_segments>
                      <MarkdownSegment>
                        <SegmentId>2b9d46c1-5a85-4b28-8455-e8ede87cee37</SegmentId>
                        <BoldItem internal_item_id="4efe0aa8-2c54-40f2-86a8-fe981fa8ad90" internal_item_type="Bold">
                          <boldvalue>%%%20%%%</boldvalue>
                          <internal_itatic_bold_item_type>Star</internal_itatic_bold_item_type>
                        </BoldItem>
                        <InternalNormalItem internal_item_id="be03795a-7cfd-43d6-9cfc-2f1212e69884" internal_item_type="Normal">
                          <internalitemvalue>%%%21%%%</internalitemvalue>
                        </InternalNormalItem>
                      </MarkdownSegment>
                      <MarkdownSegment>
                        <SegmentId>860d5b23-9ee5-44df-ae50-ca1978cf512f</SegmentId>
                        <InternalNormalItem internal_item_id="c178c01e-a91b-452e-95f8-4db9495d0974" internal_item_type="Normal">
                          <internalitemvalue>%%%22%%%</internalitemvalue>
                        </InternalNormalItem>
                      </MarkdownSegment>
                      <MarkdownSegment>
                        <SegmentId>dd3431f5-f798-43e1-b1be-d0804ac439cb</SegmentId>
                        <InternalNormalItem internal_item_id="7c08c1c2-264a-480e-a66f-10e714b45f32" internal_item_type="Normal">
                          <internalitemvalue>%%%23%%%</internalitemvalue>
                        </InternalNormalItem>
                      </MarkdownSegment>
                    </paragraph_segments>
                  </MarkdownParagraphBlock>
                </ListItem>
                <ListItem>
                  <MarkdownParagraphBlock item_id="4c84d814-ad09-4f02-965a-f45ec70b2542" item_type="NormalParagraph">
                    <paragraph_segments>
                      <MarkdownSegment>
                        <SegmentId>cbf19307-d35e-49bc-bd4f-e242cd83dab8</SegmentId>
                        <BoldItem internal_item_id="f7934929-ff13-4d3a-bd65-199f3221c5bf" internal_item_type="Bold">
                          <boldvalue>%%%24%%%</boldvalue>
                          <internal_itatic_bold_item_type>Star</internal_itatic_bold_item_type>
                        </BoldItem>
                        <InternalNormalItem internal_item_id="635287a0-57f4-48b5-a3d6-78e8e01ee022" internal_item_type="Normal">
                          <internalitemvalue>%%%25%%%</internalitemvalue>
                        </InternalNormalItem>
                      </MarkdownSegment>
                      <MarkdownSegment>
                        <SegmentId>b8fdb663-0e00-43c7-a938-49c502004e93</SegmentId>
                        <InternalNormalItem internal_item_id="5e701584-d692-432d-bc51-5b9b307ca1c5" internal_item_type="Normal">
                          <internalitemvalue>%%%26%%%</internalitemvalue>
                        </InternalNormalItem>
                      </MarkdownSegment>
                    </paragraph_segments>
                  </MarkdownParagraphBlock>
                </ListItem>
                <ListItem>
                  <MarkdownParagraphBlock item_id="ce8ef9dc-a5ae-44ce-abd8-2e0d3be64074" item_type="NormalParagraph">
                    <paragraph_segments>
                      <MarkdownSegment>
                        <SegmentId>a43c9a08-820a-42ca-8f0b-401aaca73dcc</SegmentId>
                        <BoldItem internal_item_id="f2326b4b-d941-4dfb-b369-3c10d312ecd1" internal_item_type="Bold">
                          <boldvalue>%%%27%%%</boldvalue>
                          <internal_itatic_bold_item_type>Star</internal_itatic_bold_item_type>
                        </BoldItem>
                        <InternalNormalItem internal_item_id="2c8b9ec1-7485-4f35-addd-814c7ac411f8" internal_item_type="Normal">
                          <internalitemvalue>%%%28%%%</internalitemvalue>
                        </InternalNormalItem>
                      </MarkdownSegment>
                      <MarkdownSegment>
                        <SegmentId>4f43d7f9-36b9-4196-94ec-0c0895fcd451</SegmentId>
                        <InternalNormalItem internal_item_id="6c07c4e5-1ad6-4816-bcf6-027103048997" internal_item_type="Normal">
                          <internalitemvalue>%%%29%%%</internalitemvalue>
                        </InternalNormalItem>
                      </MarkdownSegment>
                      <MarkdownSegment>
                        <SegmentId>a7a5fb09-17c7-4740-abb1-045644763cb6</SegmentId>
                        <InternalNormalItem internal_item_id="ead02f54-726d-4898-957f-83dd114f26ab" internal_item_type="Normal">
                          <internalitemvalue>%%%30%%%</internalitemvalue>
                        </InternalNormalItem>
                      </MarkdownSegment>
                      <MarkdownSegment>
                        <SegmentId>e70e7305-f900-4b1a-aae7-d6418819f052</SegmentId>
                        <InternalNormalItem internal_item_id="5bddbeb3-6671-4620-84b0-1599d8a655cf" internal_item_type="Normal">
                          <internalitemvalue>%%%31%%%</internalitemvalue>
                        </InternalNormalItem>
                      </MarkdownSegment>
                      <MarkdownSegment>
                        <SegmentId>332a8c4b-ba2b-4ccf-9f82-6aa2bfd1bd2b</SegmentId>
                        <InternalNormalItem internal_item_id="fece6aa2-50d7-43ed-af7e-c7390354a616" internal_item_type="Normal">
                          <internalitemvalue>%%%32%%%</internalitemvalue>
                        </InternalNormalItem>
                      </MarkdownSegment>
                    </paragraph_segments>
                  </MarkdownParagraphBlock>
                </ListItem>
              </inner_list_items>
              <ListType>Charactor</ListType>
            </MarkdownListBlock>
            <MarkdownHeaderBlock item_id="45e20449-15d3-46cf-988f-e188eec3f693" item_type="Header">
              <headervalue>%%%33%%%</headervalue>
              <header_type>Star</header_type>
              <header_level>2</header_level>
            </MarkdownHeaderBlock>
            <MarkdownParagraphBlock item_id="ebd598f5-112e-4f2f-b47d-d05d40c123a8" item_type="NormalParagraph">
              <paragraph_segments>
                <MarkdownSegment>
                  <SegmentId>78da59ff-dbce-439b-a08f-44dcd6667ec8</SegmentId>
                  <InternalNormalItem internal_item_id="167016ef-c068-451e-88eb-32a02d8f861e" internal_item_type="Normal">
                    <internalitemvalue>%%%34%%%</internalitemvalue>
                  </InternalNormalItem>
                </MarkdownSegment>
              </paragraph_segments>
            </MarkdownParagraphBlock>
            <MarkdownHeaderBlock item_id="8cf538c0-0c55-4810-a923-712f43acd647" item_type="Header">
              <headervalue>%%%35%%%</headervalue>
              <header_type>Star</header_type>
              <header_level>3</header_level>
            </MarkdownHeaderBlock>
            <MarkdownParagraphBlock item_id="37b8b3eb-a8c7-46aa-be5d-88aaf766b205" item_type="NormalParagraph">
              <paragraph_segments>
                <MarkdownSegment>
                  <SegmentId>d9c889b9-f7a6-40e5-8113-2599a9d21404</SegmentId>
                  <InternalNormalItem internal_item_id="c4d08b6c-1130-402a-9d59-226ad24b687a" internal_item_type="Normal">
                    <internalitemvalue>%%%36%%%</internalitemvalue>
                  </InternalNormalItem>
                </MarkdownSegment>
              </paragraph_segments>
            </MarkdownParagraphBlock>
            <MarkdownListBlock item_id="030bdaf3-fd65-48d5-9c13-29b14c3abad2" item_type="List">
              <inner_list_items>
                <ListItem>
                  <MarkdownParagraphBlock item_id="eed8a80e-e056-4441-8bc5-93c7800ca97f" item_type="NormalParagraph">
                    <paragraph_segments>
                      <MarkdownSegment>
                        <SegmentId>8b35709a-bf41-4d48-959f-9aa413002c41</SegmentId>
                        <LinkItem internal_item_id="55476851-c7fd-4d21-bd81-71cd343b0526" internal_item_type="Link">
                          <internal_link_type>Inline</internal_link_type>
                          <internal_link_text>%%%37%%%</internal_link_text>
                          <internal_link_url>../app-service-web-overview</internal_link_url>
                          <internal_link_title />
                        </LinkItem>
                        <InternalNormalItem internal_item_id="14c4cb87-0f2a-4ebc-954a-2314661bc28c" internal_item_type="Normal">
                          <internalitemvalue>%%%38%%%</internalitemvalue>
                        </InternalNormalItem>
                      </MarkdownSegment>
                    </paragraph_segments>
                  </MarkdownParagraphBlock>
                </ListItem>
                <ListItem>
                  <MarkdownParagraphBlock item_id="2aaa6694-d0c7-44d7-a585-8ad53ee1eaa5" item_type="NormalParagraph">
                    <paragraph_segments>
                      <MarkdownSegment>
                        <SegmentId>6c7f0999-e4cc-4ddc-86fb-7225e9502e1b</SegmentId>
                        <LinkItem internal_item_id="67aeffeb-b779-47c7-8f79-1d8a4433cf85" internal_item_type="Link">
                          <internal_link_type>Inline</internal_link_type>
                          <internal_link_text>%%%39%%%</internal_link_text>
                          <internal_link_url>../app-service-mobile-value-prop-preview</internal_link_url>
                          <internal_link_title />
                        </LinkItem>
                        <InternalNormalItem internal_item_id="7cffdd5d-41aa-4bf8-9d1d-1aa319572717" internal_item_type="Normal">
                          <internalitemvalue>%%%40%%%</internalitemvalue>
                        </InternalNormalItem>
                      </MarkdownSegment>
                    </paragraph_segments>
                  </MarkdownParagraphBlock>
                </ListItem>
                <ListItem>
                  <MarkdownParagraphBlock item_id="dbb1375e-3a58-4298-8f24-f214bfbf73ee" item_type="NormalParagraph">
                    <paragraph_segments>
                      <MarkdownSegment>
                        <SegmentId>2e7a5963-e6da-463d-a05c-2032c9a74498</SegmentId>
                        <LinkItem internal_item_id="aa8351ff-cf8e-4fdf-9619-a3087324dedd" internal_item_type="Link">
                          <internal_link_type>Inline</internal_link_type>
                          <internal_link_text>%%%41%%%</internal_link_text>
                          <internal_link_url>../app-service-api-apps-why-best-platform</internal_link_url>
                          <internal_link_title />
                        </LinkItem>
                        <InternalNormalItem internal_item_id="ce32c343-0414-4870-b7da-7a728eb5c93d" internal_item_type="Normal">
                          <internalitemvalue>%%%42%%%</internalitemvalue>
                        </InternalNormalItem>
                      </MarkdownSegment>
                    </paragraph_segments>
                  </MarkdownParagraphBlock>
                </ListItem>
                <ListItem>
                  <MarkdownParagraphBlock item_id="7186776c-7d13-47a9-bb00-262261335cb6" item_type="NormalParagraph">
                    <paragraph_segments>
                      <MarkdownSegment>
                        <SegmentId>251b0d92-8c89-4519-bcb9-dfc56b10a305</SegmentId>
                        <LinkItem internal_item_id="0fc307f0-f720-45e1-ac3d-6a4b638d936f" internal_item_type="Link">
                          <internal_link_type>Inline</internal_link_type>
                          <internal_link_text>%%%43%%%</internal_link_text>
                          <internal_link_url>../app-service-logic-what-are-logic-apps</internal_link_url>
                          <internal_link_title />
                        </LinkItem>
                        <InternalNormalItem internal_item_id="8f74e4fe-9654-48df-97ed-15f24e327253" internal_item_type="Normal">
                          <internalitemvalue>%%%44%%%</internalitemvalue>
                        </InternalNormalItem>
                      </MarkdownSegment>
                    </paragraph_segments>
                  </MarkdownParagraphBlock>
                </ListItem>
              </inner_list_items>
              <ListType>Charactor</ListType>
            </MarkdownListBlock>
            <MarkdownParagraphBlock item_id="b6709cfb-802a-4d68-a727-b65928224d05" item_type="NormalParagraph">
              <paragraph_segments>
                <MarkdownSegment>
                  <SegmentId>cbffa9ae-2bb5-4f2a-a3fa-9d834e9b84a4</SegmentId>
                  <InternalNormalItem internal_item_id="88f4e2e1-f7d8-40f5-b501-8a2aa8fd6168" internal_item_type="Normal">
                    <internalitemvalue>%%%45%%%</internalitemvalue>
                  </InternalNormalItem>
                </MarkdownSegment>
              </paragraph_segments>
            </MarkdownParagraphBlock>
            <MarkdownHeaderBlock item_id="39680088-f883-4381-96da-4804c32e2733" item_type="Header">
              <headervalue>%%%46%%%</headervalue>
              <header_type>Star</header_type>
              <header_level>3</header_level>
            </MarkdownHeaderBlock>
            <MarkdownParagraphBlock item_id="e2ac92ea-0ef6-4ab6-b84d-942af8b961a9" item_type="NormalParagraph">
              <paragraph_segments>
                <MarkdownSegment>
                  <SegmentId>d7eef4c1-7ace-4033-9026-5742595eaff4</SegmentId>
                  <InternalNormalItem internal_item_id="175e1429-adce-431a-ae22-60380d3ebb05" internal_item_type="Normal">
                    <internalitemvalue>%%%47%%%</internalitemvalue>
                  </InternalNormalItem>
                </MarkdownSegment>
                <MarkdownSegment>
                  <SegmentId>b51f64a4-d8e4-485c-9c1a-25fc5a2efcf6</SegmentId>
                  <InternalNormalItem internal_item_id="4e34d562-0568-45bc-81b8-b1fe82752e2e" internal_item_type="Normal">
                    <internalitemvalue>%%%48%%%</internalitemvalue>
                  </InternalNormalItem>
                </MarkdownSegment>
                <MarkdownSegment>
                  <SegmentId>5cd0623a-0c01-47d7-98e2-6edc1abec6d7</SegmentId>
                  <InternalNormalItem internal_item_id="9b89c487-d5cc-4a5b-bd49-a0e1e7060ef7" internal_item_type="Normal">
                    <internalitemvalue>%%%49%%%</internalitemvalue>
                  </InternalNormalItem>
                </MarkdownSegment>
                <MarkdownSegment>
                  <SegmentId>6d68c10c-7ef4-46c2-93a5-4dec043a96f4</SegmentId>
                  <LinkItem internal_item_id="4bd67cee-17cb-459e-b8da-4fbb4a979c58" internal_item_type="Link">
                    <internal_link_type>Inline</internal_link_type>
                    <internal_link_text>%%%50%%%</internal_link_text>
                    <internal_link_url>../web-sites-web-hosting-plan-overview.md</internal_link_url>
                    <internal_link_title />
                  </LinkItem>
                  <InternalNormalItem internal_item_id="dc8844fd-b75e-4f99-af08-101251ccfe82" internal_item_type="Normal">
                    <internalitemvalue>%%%51%%%</internalitemvalue>
                  </InternalNormalItem>
                </MarkdownSegment>
              </paragraph_segments>
            </MarkdownParagraphBlock>
            <MarkdownHeaderBlock item_id="cc5bcfbc-8b56-4e2b-8a31-809f9bab9657" item_type="Header">
              <headervalue>%%%52%%%</headervalue>
              <header_type>Star</header_type>
              <header_level>2</header_level>
            </MarkdownHeaderBlock>
            <MarkdownParagraphBlock item_id="44868fd0-96dc-4bfb-be01-2ec41b7c0a2d" item_type="NormalParagraph">
              <paragraph_segments>
                <MarkdownSegment>
                  <SegmentId>db8ec31a-32df-4600-a11b-ea564193628b</SegmentId>
                  <InternalNormalItem internal_item_id="c3c43388-ad70-4e9c-a88d-0002cfb499a5" internal_item_type="Normal">
                    <internalitemvalue>%%%53%%%</internalitemvalue>
                  </InternalNormalItem>
                </MarkdownSegment>
                <MarkdownSegment>
                  <SegmentId>1fc25065-96f1-4849-b11d-3f893f3d3718</SegmentId>
                  <InternalNormalItem internal_item_id="d194c140-bcea-4bf6-b1c8-0870aed962c6" internal_item_type="Normal">
                    <internalitemvalue>%%%54%%%</internalitemvalue>
                  </InternalNormalItem>
                </MarkdownSegment>
              </paragraph_segments>
            </MarkdownParagraphBlock>
            <MarkdownParagraphBlock item_id="216bce49-c840-4efd-9553-a558f538d392" item_type="NormalParagraph">
              <paragraph_segments>
                <MarkdownSegment>
                  <SegmentId>c0b854fb-af4c-4abd-a619-981db892c5e8</SegmentId>
                  <InternalNormalItem internal_item_id="03b38d5c-894b-4b10-af76-e6798a3702f8" internal_item_type="Normal">
                    <internalitemvalue>%%%55%%%</internalitemvalue>
                  </InternalNormalItem>
                </MarkdownSegment>
              </paragraph_segments>
            </MarkdownParagraphBlock>
            <MarkdownParagraphBlock item_id="b9b3fe0c-51f8-4758-9207-a3e826c70771" item_type="NormalParagraph">
              <paragraph_segments>
                <MarkdownSegment>
                  <SegmentId>77debf5b-8cf1-4118-b24a-cbf700b2f66d</SegmentId>
                  <LinkItem internal_item_id="1a904463-e67c-4762-82a6-7fcc4ac85f35" internal_item_type="Link">
                    <internal_link_type>Inline</internal_link_type>
                    <internal_link_text>%%%56%%%</internal_link_text>
                    <internal_link_url>http://go.microsoft.com/fwlink/?LinkId=523751</internal_link_url>
                    <internal_link_title />
                  </LinkItem>
                  <InternalNormalItem internal_item_id="63646eab-b3cc-4d90-98b2-a4579490ca2f" internal_item_type="Normal">
                    <internalitemvalue>%%%57%%%</internalitemvalue>
                  </InternalNormalItem>
                </MarkdownSegment>
                <MarkdownSegment>
                  <SegmentId>5cff6185-827e-4ec0-83b3-619bddf0afc1</SegmentId>
                  <InternalNormalItem internal_item_id="8b747522-421d-450d-9db0-4379c7fa1686" internal_item_type="Normal">
                    <internalitemvalue>%%%58%%%</internalitemvalue>
                  </InternalNormalItem>
                </MarkdownSegment>
              </paragraph_segments>
            </MarkdownParagraphBlock>
          </MarkdownContent>
        </block_element>
      </markdown_skeleton_root>
    </xliffext:content>
  </xliffext:skl>
</xliffext:root>